pyrebase/__init__.py
pyrebase/pyre_sseclient.py
pyrebase/pyrebase.py
pyrebase_air-4.11.0.dist-info/METADATA
pyrebase_air-4.11.0.dist-info/WHEEL
pyrebase_air-4.11.0.dist-info/top_level.txt
pyrebase_air-4.11.0.dist-info/RECORD
