Metadata-Version: 2.4
Name: pyrebase_air
Version: 4.11.0
Summary: A simple python wrapper for the Firebase API with current deps
Home-page: https://github.com/kbirger/pyrebase-air
Author: kbirger
License: MIT
Keywords: Firebase
Classifier: Development Status :: 3 - Alpha
Classifier: Intended Audience :: Developers
Classifier: License :: OSI Approved :: MIT License
Classifier: Programming Language :: Python :: 3.4
Requires-Dist: requests-toolbelt>=1.0.0
Requires-Dist: requests>=2.31
Requires-Dist: urllib3>=2.0
Requires-Dist: gcloud>=0.18.3
Requires-Dist: oauth2client>=4.1.2
Requires-Dist: python-jwt>=2.0.1
Requires-Dist: pycryptodome>=3.6.4
Dynamic: author
Dynamic: classifier
Dynamic: home-page
Dynamic: keywords
Dynamic: license
Dynamic: requires-dist
Dynamic: summary
